pureskillgg_dsdk/__init__.py
pureskillgg_dsdk/adx/__init__.py
pureskillgg_dsdk/adx/api.py
pureskillgg_dsdk/adx/dataset.py
pureskillgg_dsdk/adx/writer_fs.py
pureskillgg_dsdk/adx/writer_s3.py
pureskillgg_dsdk/ds_io/__init__.py
pureskillgg_dsdk/ds_io/game_ds_loader.py
pureskillgg_dsdk/ds_io/game_ds_loader_test.py
pureskillgg_dsdk/ds_io/handle_value_error.py
pureskillgg_dsdk/ds_io/normalize_instructions.py
pureskillgg_dsdk/ds_io/normalize_instructions_test.py
pureskillgg_dsdk/ds_io/reader_fs.py
pureskillgg_dsdk/ds_io/reader_s3.py
pureskillgg_dsdk/ds_models/__init__.py
pureskillgg_dsdk/ds_models/find.py
pureskillgg_dsdk/ds_models/model.py
pureskillgg_dsdk/ds_models/model_test.py
pureskillgg_dsdk/ds_models/s3_dataframe.py
pureskillgg_dsdk/ds_models/s3_dataframe_set.py
pureskillgg_dsdk/ds_models/s3_hashmap.py
pureskillgg_dsdk/ds_models/s3_model.py
pureskillgg_dsdk/ds_models/s3_scikit.py
pureskillgg_dsdk/ds_models/s3_scikit_set.py
pureskillgg_dsdk/ds_models/sagemaker_endpoint.py
pureskillgg_dsdk/tome/__init__.py
pureskillgg_dsdk/tome/constants.py
pureskillgg_dsdk/tome/curator.py
pureskillgg_dsdk/tome/curator_test.py
pureskillgg_dsdk/tome/factory.py
pureskillgg_dsdk/tome/header_copier_fs.py
pureskillgg_dsdk/tome/header_tome.py
pureskillgg_dsdk/tome/loader.py
pureskillgg_dsdk/tome/maker.py
pureskillgg_dsdk/tome/manifest.py
pureskillgg_dsdk/tome/reader_fs.py
pureskillgg_dsdk/tome/scribe.py
pureskillgg_dsdk/tome/writer_fs.py
pureskillgg_dsdk-2.0.0.dist-info/LICENSE.txt
pureskillgg_dsdk-2.0.0.dist-info/WHEEL
pureskillgg_dsdk-2.0.0.dist-info/METADATA
pureskillgg_dsdk-2.0.0.dist-info/RECORD
