Metadata-Version: 2.1
Name: pureskillgg-dsdk
Version: 2.0.0
Summary: Python Data Science Development Kit.
Home-page: https://github.com/pureskillgg/dsdk
License: MIT
Author: PureSkill.gg
Author-email: contact@pureskill.gg
Requires-Python: >=3.9,<4.0
Classifier: License :: OSI Approved :: MIT License
Classifier: Programming Language :: Python :: 3
Classifier: Programming Language :: Python :: 3.9
Classifier: Programming Language :: Python :: 3.10
Requires-Dist: boto3 (>=1.34.41,<2.0.0)
Requires-Dist: pandas[aws,computation,fss,output-formatting,parquet,performance,plot] (>=2.2.1,<3.0.0)
Requires-Dist: pyarrow (>=14.0.0,<14.1.0)
Requires-Dist: python-rapidjson (>=1.6,<2.0)
Requires-Dist: structlog (>=22.1.0,<23.0.0)
Project-URL: Repository, https://github.com/pureskillgg/dsdk
